fqsdfqsdfqsdfqsd/__init__.py
fqsdfqsdfqsdfqsd/config.py
fqsdfqsdfqsdfqsd/contracts/__init__.py
fqsdfqsdfqsdfqsd/contracts/deal_contract.py
fqsdfqsdfqsdfqsd/contracts/match_contract.py
fqsdfqsdfqsdfqsd/contracts/repayment_contract.py
fqsdfqsdfqsdfqsd/contracts/reserve_contract.py
fqsdfqsdfqsdfqsd/funds/__init__.py
fqsdfqsdfqsdfqsd/funds/credit_fund.py
fqsdfqsdfqsdfqsd/oracles/__init__.py
fqsdfqsdfqsdfqsd/oracles/pricing_oracle.py
fqsdfqsdfqsdfqsd/simulations/__init__.py
fqsdfqsdfqsdfqsd/simulations/main_simulation.py
fqsdfqsdfqsdfqsd/tokens/NFT.py
fqsdfqsdfqsdfqsd/tokens/RT.py
fqsdfqsdfqsdfqsd/tokens/UT.py
fqsdfqsdfqsdfqsd/tokens/__init__.py
fqsdfqsdfqsdfqsd/wallets/__init__.py
fqsdfqsdfqsdfqsd/wallets/credix_wallet.py
fqsdfqsdfqsdfqsd/wallets/investor_wallet.py
fqsdfqsdfqsdfqsd/wallets/underwriter_wallet.py
fqsdfqsdfqsdfqsd/wallets/wallet.py
fqsdfqsdfqsdfqsd-0.16.dist-info/METADATA
fqsdfqsdfqsdfqsd-0.16.dist-info/WHEEL
fqsdfqsdfqsdfqsd-0.16.dist-info/top_level.txt
fqsdfqsdfqsdfqsd-0.16.dist-info/RECORD
