Metadata-Version: 2.1
Name: fqsdfqsdfqsdfqsd
Version: 0.16
Summary: fqsdfqsdfqsdfqsd
Home-page: UNKNOWN
Author: fqsdfqsdfqsdfqsd
Author-email: fqsdfqsdfqsdfqsdn@gmail.com
License: MIT
Platform: UNKNOWN
Requires-Dist: python-dateutil
Requires-Dist: pandas
